schema_registry_python/__init__.py
schema_registry_python/cli.py
schema_registry_python-0.1.0.dist-info/WHEEL
schema_registry_python-0.1.0.dist-info/METADATA
schema_registry_python-0.1.0.dist-info/entry_points.txt
schema_registry_python-0.1.0.dist-info/RECORD
